unittest_resources/__init__.py
unittest_resources/testing.py
unittest_resources/tests/__init__.py
unittest_resources/tests/test_classes.py
unittest_resources/tests/test_code.py
unittest_resources-0.2.0.dist-info/LICENSE
unittest_resources-0.2.0.dist-info/METADATA
unittest_resources-0.2.0.dist-info/WHEEL
unittest_resources-0.2.0.dist-info/top_level.txt
unittest_resources-0.2.0.dist-info/zip-safe
unittest_resources-0.2.0.dist-info/RECORD
