Metadata-Version: 2.1
Name: unittest-resources
Version: 0.2.0
Summary: Dynamic resource-based unittest suites made easy.
Home-page: https://gitlab.com/ergoithz/unittest-resources
Author: Felipe A. Hernandez
Author-email: ergoithz@gmail.com
License: MIT
Platform: any
Classifier: Programming Language :: Python :: 2
Classifier: Programming Language :: Python :: 3
Classifier: Development Status :: 4 - Beta
Classifier: License :: OSI Approved :: MIT License
Classifier: Topic :: Software Development :: Testing :: Unit
Provides-Extra: testing-maintainability
Provides-Extra: testing-style
Provides-Extra: testing
Provides-Extra: testing-typing
